<?xml version="1.0"?>

<PropertyList>

<path>hdg-gauge.ac</path>

    <animation>
        <type>material</type>
        <object-name>HDGpointer</object-name>
        <object-name>HDGneedle</object-name>
        <emission>
            <red>0.5</red>
            <green>0.2</green>
            <blue>0.0</blue>
            <factor-prop>/systems/electrical/outputs/instrument-lights</factor-prop>
        </emission>
    </animation>

    <animation>
        <type>texrotate</type>
        <object-name>HDGneedle</object-name>
        <property>/instrumentation/heading-indicator/indicated-heading-deg</property>
        <axis>
            <x>0.0</x>
            <y>0.0</y>
            <z>-1.0</z>
        </axis>
        <center>
            <x>0.5</x>
            <y>0.5</y>
        </center>
    </animation>

</PropertyList>